winenv/__init__.py
winenv-1.0.1.dist-info/METADATA
winenv-1.0.1.dist-info/WHEEL
winenv-1.0.1.dist-info/top_level.txt
winenv-1.0.1.dist-info/RECORD
