Metadata-Version: 2.1
Name: winenv
Version: 1.0.1
Summary: Python library to extract the current windows environment (ignores the session).
Home-page: https://github.com/hweickert/winenv
Author: Henry Weickert
Author-email: henryweickert@gmail.com
License: UNKNOWN
Platform: UNKNOWN
